Workbook
Name CARGO: [1]Auxiliar!$B$2:$B$5
Name SEXO: [1]Auxiliar!$A$2:$A$3

Sheet VertiPinturas Data Formats
A1: DATA Vertipinturas
B3: Sales per week to stores (liters of paint)
B4: Color122 | C4: Color 202 | D4: Color323 | E4: Color678 | F4: Color856 | G4: Color900 | H4: TOTAL
A5: Store 1 | B5: 43 | C5: 52 | D5: 55 | E5: 63 | F5: 49 | G5: 65 | H5: =SUM(B5:G5) -> 327
A6: Store 2 | B6: 90 | C6: 67 | D6: 38 | E6: 36 | F6: 76 | G6: 56 | H6: =SUM(B6:G6) -> 363
A7: Store 3 | B7: 44 | C7: 32 | D7: 56 | E7: 45 | F7: 67 | G7: 78 | H7: =SUM(B7:G7) -> 322
A8: Store 4 | B8: 55 | C8: 44 | D8: 54 | E8: 89 | F8: 88 | G8: 67 | H8: =SUM(B8:G8) -> 397
A9: Store 5 | B9: 56 | C9: 46 | D9: 90 | E9: 56 | F9: 55 | G9: 98 | H9: =SUM(B9:G9) -> 401
A10: Store 6 | B10: 24 | C10: 36 | D10: 56 | E10: 54 | F10: 66 | G10: 64 | H10: =SUM(B10:G10) -> 300
A11: Total | B11: =SUM(B5:B10) -> 312 | C11: =SUM(C5:C10) -> 277 | D11: =SUM(D5:D10) -> 349 | E11: =SUM(E5:E10) -> 343 | F11: =SUM(F5:F10) -> 401 | G11: =SUM(G5:G10) -> 428 | H11: =SUM(B11:G11) -> 2110
A13: Revenue Volume Discounts | E13: VERTIPAINTINGS´COSTS
A14: Up to | B14: 700 | C14: 0.05 | E14: Manufacturer distribution costs | H14: 1250
A15: Between 701 | B15: 900 | C15: 0.08 | E15: Product cost over total sales | H15: 0.25
A16: Más de | B16: 900 | C16: 0.12
A17: Note: the discount is applied to the total income of each dealer
B19: Manufacturer's selling price, for paint types, per 5 liters.
B20: Color122 | C20: Color 202 | D20: Color323 | E20: Color678 | F20: Color856 | G20: Color900
B21: 15 | C21: 17 | D21: 11.5 | E21: 12 | F21: 14 | G21: 18
A22: DATA per store | B22: =B21/5 -> 3 | C22: =C21/5 -> 3.4 | D22: =D21/5 -> 2.3 | E22: =E21/5 -> 2.4 | F22: =F21/5 -> 2.8 | G22: =G21/5 -> 3.6
B23: variable costs for each store
B24: Tienda 1 | C24: Tienda 2 | D24: Tienda 3 | E24: Tienda 4 | F24: Tienda 5 | G24: Tienda 6
A25: Color122 | B25: 6.6 | C25: 7.8 | D25: 8.6 | E25: 9.8 | F25: 10.9 | G25: 11.6
A26: Color 202 | B26: 7.8 | C26: 8.3 | D26: 9.1 | E26: 9.4 | F26: 10.8 | G26: 12.3
A27: Color323 | B27: 6.3 | C27: 7.7 | D27: 8.8 | E27: 10.2 | F27: 11.1 | G27: 12.1
A28: Color678 | B28: 6.1 | C28: 8.2 | D28: 8.5 | E28: 9.7 | F28: 12 | G28: 11.9
A29: Color856 | B29: 6.9 | C29: 8.4 | D29: 8.4 | E29: 9.6 | F29: 11.5 | G29: 12.8
A30: Color900 | B30: 5.9 | C30: 8.1 | D30: 8.9 | E30: 9.9 | F30: 11.1 | G30: 12
B32: Fixed costs for each store
B33: Store 1 | C33: Store 2 | D33: Store 3 | E33: Store 4 | F33: Store 5 | G33: Store 6
B34: 75 | C34: 91 | D34: 121 | E34: 68 | F34: 106 | G34: 104
B36: Retail price (per liter) at stores
B37: Color122 | C37: Color 202 | D37: Color323 | E37: Color678 | F37: Color856 | G37: Color900
B38: 20 | C38: 23 | D38: 22 | E38: 24 | F38: 18 | G38: 20

Sheet Vertipinturas oper & ref
A1: wholesaler
B2: Sales in euros of the main company: VertiPinturas | J2: 2023 | K2: 2024 | L2: 2024
B3: Color122 | C3: Color 202 | D3: Color323 | E3: Color678 | F3: Color856 | G3: Color900 | H3: Income | I3: Discount | J3: Final Income | K3: Final Income | L3: Sum percentage increase | M3: Absolute change | N3: Relative rate of change
A4: Store 1 | B4: ='VertiPinturas Data Formats'!B5*'VertiPinturas Data Formats'!$B$22 -> 129 | C4: ='VertiPinturas Data Formats'!C5*'VertiPinturas Data Formats'!$C$22 -> 176.8 | D4: ='VertiPinturas Data Formats'!D5*'VertiPinturas Data Formats'!$D$22 -> 126.5 | E4: ='VertiPinturas Data Formats'!E5*'VertiPinturas Data Formats'!$E$22 -> 151.2 | F4: ='VertiPinturas Data Formats'!F5*'VertiPinturas Data Formats'!$F$22 -> 137.2 | G4: ='VertiPinturas Data Formats'!G5*'VertiPinturas Data Formats'!$G$22 -> 234 | H4: =SUM(B4:G4) -> 954.7 | I4: =H4*'VertiPinturas Data Formats'!$C$16 -> 114.564 | J4: =H4-I4 -> 840.136 | K4: =J4*(1+0.03) -> 865.34008 | L4: =J4*1.03 -> 865.34008 | M4: =L4-J4 -> 25.20408 | N4: =(L4/J4)-1 -> 0.03
A5: Store 2 | B5: ='VertiPinturas Data Formats'!B6*'VertiPinturas Data Formats'!$B$22 -> 270 | C5: ='VertiPinturas Data Formats'!C6*'VertiPinturas Data Formats'!$C$22 -> 227.8 | D5: ='VertiPinturas Data Formats'!D6*'VertiPinturas Data Formats'!$D$22 -> 87.4 | E5: ='VertiPinturas Data Formats'!E6*'VertiPinturas Data Formats'!$E$22 -> 86.4 | F5: ='VertiPinturas Data Formats'!F6*'VertiPinturas Data Formats'!$F$22 -> 212.8 | G5: ='VertiPinturas Data Formats'!G6*'VertiPinturas Data Formats'!$G$22 -> 201.6 | H5: =SUM(B5:G5) -> 1086 | I5: =H5*'VertiPinturas Data Formats'!$C$16 -> 130.32 | J5: =H5-I5 -> 955.68 | K5: =J5*(1+0.03) -> 984.3504 | L5: =J5*1.03 -> 984.3504 | M5: =L5-J5 -> 28.6704 | N5: =(L5/J5)-1 -> 0.03
A6: Store 3 | B6: ='VertiPinturas Data Formats'!B7*'VertiPinturas Data Formats'!$B$22 -> 132 | C6: ='VertiPinturas Data Formats'!C7*'VertiPinturas Data Formats'!$C$22 -> 108.8 | D6: ='VertiPinturas Data Formats'!D7*'VertiPinturas Data Formats'!$D$22 -> 128.8 | E6: ='VertiPinturas Data Formats'!E7*'VertiPinturas Data Formats'!$E$22 -> 108 | F6: ='VertiPinturas Data Formats'!F7*'VertiPinturas Data Formats'!$F$22 -> 187.6 | G6: ='VertiPinturas Data Formats'!G7*'VertiPinturas Data Formats'!$G$22 -> 280.8 | H6: =SUM(B6:G6) -> 946 | I6: =H6*'VertiPinturas Data Formats'!$C$16 -> 113.52 | J6: =H6-I6 -> 832.48 | K6: =J6*(1+0.03) -> 857.4544 | L6: =J6*1.03 -> 857.4544 | M6: =L6-J6 -> 24.9744 | N6: =(L6/J6)-1 -> 0.03
A7: Store 4 | B7: ='VertiPinturas Data Formats'!B8*'VertiPinturas Data Formats'!$B$22 -> 165 | C7: ='VertiPinturas Data Formats'!C8*'VertiPinturas Data Formats'!$C$22 -> 149.6 | D7: ='VertiPinturas Data Formats'!D8*'VertiPinturas Data Formats'!$D$22 -> 124.2 | E7: ='VertiPinturas Data Formats'!E8*'VertiPinturas Data Formats'!$E$22 -> 213.6 | F7: ='VertiPinturas Data Formats'!F8*'VertiPinturas Data Formats'!$F$22 -> 246.4 | G7: ='VertiPinturas Data Formats'!G8*'VertiPinturas Data Formats'!$G$22 -> 241.2 | H7: =SUM(B7:G7) -> 1140 | I7: =H7*'VertiPinturas Data Formats'!$C$16 -> 136.8 | J7: =H7-I7 -> 1003.2 | K7: =J7*(1+0.03) -> 1033.296 | L7: =J7*1.03 -> 1033.296 | M7: =L7-J7 -> 30.096 | N7: =(L7/J7)-1 -> 0.03
A8: Store 5 | B8: ='VertiPinturas Data Formats'!B9*'VertiPinturas Data Formats'!$B$22 -> 168 | C8: ='VertiPinturas Data Formats'!C9*'VertiPinturas Data Formats'!$C$22 -> 156.4 | D8: ='VertiPinturas Data Formats'!D9*'VertiPinturas Data Formats'!$D$22 -> 207 | E8: ='VertiPinturas Data Formats'!E9*'VertiPinturas Data Formats'!$E$22 -> 134.4 | F8: ='VertiPinturas Data Formats'!F9*'VertiPinturas Data Formats'!$F$22 -> 154 | G8: ='VertiPinturas Data Formats'!G9*'VertiPinturas Data Formats'!$G$22 -> 352.8 | H8: =SUM(B8:G8) -> 1172.6 | I8: =H8*'VertiPinturas Data Formats'!$C$16 -> 140.712 | J8: =H8-I8 -> 1031.888 | K8: =J8*(1+0.03) -> 1062.8446 | L8: =J8*1.03 -> 1062.8446 | M8: =L8-J8 -> 30.95664 | N8: =(L8/J8)-1 -> 0.03
A9: Store 6 | B9: ='VertiPinturas Data Formats'!B10*'VertiPinturas Data Formats'!$B$22 -> 72 | C9: ='VertiPinturas Data Formats'!C10*'VertiPinturas Data Formats'!$C$22 -> 122.4 | D9: ='VertiPinturas Data Formats'!D10*'VertiPinturas Data Formats'!$D$22 -> 128.8 | E9: ='VertiPinturas Data Formats'!E10*'VertiPinturas Data Formats'!$E$22 -> 129.6 | F9: ='VertiPinturas Data Formats'!F10*'VertiPinturas Data Formats'!$F$22 -> 184.8 | G9: ='VertiPinturas Data Formats'!G10*'VertiPinturas Data Formats'!$G$22 -> 230.4 | H9: =SUM(B9:G9) -> 868 | I9: =H9*'VertiPinturas Data Formats'!$C$15 -> 69.44 | J9: =H9-I9 -> 798.56 | K9: =J9*(1+0.03) -> 822.5168 | L9: =J9*1.03 -> 822.5168 | M9: =L9-J9 -> 23.9568 | N9: =(L9/J9)-1 -> 0.03
A10: Total | B10: =SUM(B4:B9) -> 936 | C10: =SUM(C4:C9) -> 941.8 | D10: =SUM(D4:D9) -> 802.7 | E10: =SUM(E4:E9) -> 823.2 | F10: =SUM(F4:F9) -> 1122.8 | G10: =SUM(G4:G9) -> 1540.8 | H10: =SUM(H4:H9) -> 6167.3 | I10: =SUM(I4:I9) -> 705.356 | ... M10: =SUM(M4:M9) -> 163.85832
A11: Company profit VERTIPINTURAS=
A13: Unit distribution cost (or each liter of paint)= | D13: ='VertiPinturas Data Formats'!H14/'VertiPinturas Data Formats'!H11 -> 0.59241706
B15: Color122 | C15: Color 202 | D15: Color323 | E15: Color678 | F15: Color856 | G15: Color900
A16: Sale price | B16: ='VertiPinturas Data Formats'!B22 -> 3 | C16: ='VertiPinturas Data Formats'!C22 -> 3.4 | D16: ='VertiPinturas Data Formats'!D22 -> 2.3 | E16: ='VertiPinturas Data Formats'!E22 -> 2.4 | F16: ='VertiPinturas Data Formats'!F22 -> 2.8 | G16: ='VertiPinturas Data Formats'!G22 -> 3.6
A17: Unit cost | B17: =$D$13+'VertiPinturas Data Formats'!$H$15*'Vertipinturas oper & ref'!B16 -> 1.3424171 | C17: =$D$13+'VertiPinturas Data Formats'!$H$15*'Vertipinturas oper & ref'!C16 -> 1.4424171 | D17: =$D$13+'VertiPinturas Data Formats'!$H$15*'Vertipinturas oper & ref'!D16 -> 1.1674171 | E17: =$D$13+'VertiPinturas Data Formats'!$H$15*'Vertipinturas oper & ref'!E16 -> 1.1924171 | F17: =$D$13+'VertiPinturas Data Formats'!$H$15*'Vertipinturas oper & ref'!F16 -> 1.2924171 | G17: =$D$13+'VertiPinturas Data Formats'!$H$15*'Vertipinturas oper & ref'!G16 -> 1.4924171
A18: Unit profit | B18: =B16-B17 -> 1.6575829 | C18: =C16-C17 -> 1.9575829 | D18: =D16-D17 -> 1.1325829 | E18: =E16-E17 -> 1.2075829 | F18: =F16-F17 -> 1.5075829 | G18: =G16-G17 -> 2.1075829
A19: Profitability | B19: =B18/B17 -> 1.2347749 | C19: =C18/C17 -> 1.3571546 | D19: =D18/D17 -> 0.97016137 | E19: =E18/E17 -> 1.0127186 | F19: =F18/F17 -> 1.1664833 | G19: =G18/G17 -> 1.4121943
A20: Total profit per color | B20: =B18*'VertiPinturas Data Formats'!B11 -> 517.16588 | C20: =C18*'VertiPinturas Data Formats'!C11 -> 542.25047 | D20: =D18*'VertiPinturas Data Formats'!D11 -> 395.27145 | E20: =E18*'VertiPinturas Data Formats'!E11 -> 414.20095 | F20: =F18*'VertiPinturas Data Formats'!F11 -> 604.54076 | G20: =G18*'VertiPinturas Data Formats'!G11 -> 902.0455 | H20: =SUM(B20:G20) -> 3375.475
A21: RETAIL
B22: Variable costs | H22: Fixed costs
B23: Color122 | C23: Color 202 | D23: Color323 | E23: Color678 | F23: Color856 | G23: Color900
A24: Store 1 | B24: ='VertiPinturas Data Formats'!B5*'VertiPinturas Data Formats'!B25 -> 283.8 | C24: ='VertiPinturas Data Formats'!C5*'VertiPinturas Data Formats'!B26 -> 405.6 | D24: ='VertiPinturas Data Formats'!D5*'VertiPinturas Data Formats'!B27 -> 346.5 | E24: ='VertiPinturas Data Formats'!E5*'VertiPinturas Data Formats'!B28 -> 384.3 | F24: ='VertiPinturas Data Formats'!F5*'VertiPinturas Data Formats'!B29 -> 338.1 | G24: ='VertiPinturas Data Formats'!G5*'VertiPinturas Data Formats'!B30 -> 383.5 | H24: 75
A25: Store 2 | B25: ='VertiPinturas Data Formats'!B6*'VertiPinturas Data Formats'!C25 -> 702 | C25: ='VertiPinturas Data Formats'!C6*'VertiPinturas Data Formats'!C26 -> 556.1 | D25: ='VertiPinturas Data Formats'!D6*'VertiPinturas Data Formats'!C27 -> 292.6 | E25: ='VertiPinturas Data Formats'!E6*'VertiPinturas Data Formats'!C28 -> 295.2 | F25: ='VertiPinturas Data Formats'!F6*'VertiPinturas Data Formats'!C29 -> 638.4 | G25: ='VertiPinturas Data Formats'!G6*'VertiPinturas Data Formats'!C30 -> 453.6 | H25: 91
A26: Store 3 | B26: ='VertiPinturas Data Formats'!B7*'VertiPinturas Data Formats'!D25 -> 378.4 | C26: ='VertiPinturas Data Formats'!C7*'VertiPinturas Data Formats'!D26 -> 291.2 | D26: ='VertiPinturas Data Formats'!D7*'VertiPinturas Data Formats'!D27 -> 492.8 | E26: ='VertiPinturas Data Formats'!E7*'VertiPinturas Data Formats'!D28 -> 382.5 | F26: ='VertiPinturas Data Formats'!F7*'VertiPinturas Data Formats'!D29 -> 562.8 | G26: ='VertiPinturas Data Formats'!G7*'VertiPinturas Data Formats'!D30 -> 694.2 | H26: 121
A27: Store 4 | B27: ='VertiPinturas Data Formats'!B8*'VertiPinturas Data Formats'!E25 -> 539 | C27: ='VertiPinturas Data Formats'!E26*'VertiPinturas Data Formats'!C8 -> 413.6 | D27: ='VertiPinturas Data Formats'!D8*'VertiPinturas Data Formats'!E27 -> 550.8 | E27: ='VertiPinturas Data Formats'!E8*'VertiPinturas Data Formats'!E28 -> 863.3 | F27: ='VertiPinturas Data Formats'!F8*'VertiPinturas Data Formats'!E29 -> 844.8 | G27: ='VertiPinturas Data Formats'!G8*'VertiPinturas Data Formats'!E30 -> 663.3 | H27: 68
A28: Store 5 | B28: ='VertiPinturas Data Formats'!B9*'VertiPinturas Data Formats'!F25 -> 610.4 | C28: ='VertiPinturas Data Formats'!C9*'VertiPinturas Data Formats'!F26 -> 496.8 | D28: ='VertiPinturas Data Formats'!D9*'VertiPinturas Data Formats'!F27 -> 999 | E28: ='VertiPinturas Data Formats'!E9*'VertiPinturas Data Formats'!F28 -> 672 | F28: ='VertiPinturas Data Formats'!F9*'VertiPinturas Data Formats'!F29 -> 632.5 | G28: ='VertiPinturas Data Formats'!G9*'VertiPinturas Data Formats'!F30 -> 1087.8 | H28: 106
A29: Store 6 | B29: ='VertiPinturas Data Formats'!B10*'VertiPinturas Data Formats'!G25 -> 278.4 | C29: ='VertiPinturas Data Formats'!C10*'VertiPinturas Data Formats'!G26 -> 442.8 | D29: ='VertiPinturas Data Formats'!D10*'VertiPinturas Data Formats'!G27 -> 677.6 | E29: ='VertiPinturas Data Formats'!E10*'VertiPinturas Data Formats'!G28 -> 642.6 | F29: ='VertiPinturas Data Formats'!F10*'VertiPinturas Data Formats'!G29 -> 844.8 | G29: ='VertiPinturas Data Formats'!G10*'VertiPinturas Data Formats'!G30 -> 768 | H29: 104
B31: Total income | C31: Total Purchase costs | D31: Variable costs | E31: Fixed Costs | F31: Total Costs | G31: Discount | H31: Profit
A32: Store 1 | B32: ='VertiPinturas Data Formats'!B5*'VertiPinturas Data Formats'!$B$38+'VertiPinturas Data Formats'!C5*'VertiPinturas Data Formats'!$C$38+'VertiPinturas Data Formats'!D5*'VertiPinturas Data Formats'!$D$38+'VertiPinturas Data Formats'!E5*'VertiPinturas Data Formats'!$E$38+'VertiPinturas Data Formats'!F5*'VertiPinturas Data Formats'!$F$38+'VertiPinturas Data Formats'!G5*'VertiPinturas Data Formats'!$G$38 -> 6960 | C32: =H4 -> 954.7 | D32: =SUM(B24:G24) -> 2141.8 | E32: =H24 -> 75 | F32: =C32+D32+E32 -> 3171.5 | G32: =I4 -> 114.564 | H32: =B32-F32+G32 -> 3903.064
A33: Store 2 | B33: ='VertiPinturas Data Formats'!B6*'VertiPinturas Data Formats'!$B$38+'VertiPinturas Data Formats'!C6*'VertiPinturas Data Formats'!$C$38+'VertiPinturas Data Formats'!D6*'VertiPinturas Data Formats'!$D$38+'VertiPinturas Data Formats'!E6*'VertiPinturas Data Formats'!$E$38+'VertiPinturas Data Formats'!F6*'VertiPinturas Data Formats'!$F$38+'VertiPinturas Data Formats'!G6*'VertiPinturas Data Formats'!$G$38 -> 7529 | C33: =H5 -> 1086 | D33: =SUM(B25:G25) -> 2937.9 | E33: =H25 -> 91 | F33: =C33+D33+E33 -> 4114.9 | G33: =I5 -> 130.32 | H33: =B33-F33+G33 -> 3544.42
A34: Store 3 | B34: ='VertiPinturas Data Formats'!B7*'VertiPinturas Data Formats'!$B$38+'VertiPinturas Data Formats'!C7*'VertiPinturas Data Formats'!$C$38+'VertiPinturas Data Formats'!D7*'VertiPinturas Data Formats'!$D$38+'VertiPinturas Data Formats'!E7*'VertiPinturas Data Formats'!$E$38+'VertiPinturas Data Formats'!F7*'VertiPinturas Data Formats'!$F$38+'VertiPinturas Data Formats'!G7*'VertiPinturas Data Formats'!$G$38 -> 6694 | C34: =H6 -> 946 | D34: =SUM(B26:G26) -> 2801.9 | E34: =H26 -> 121 | F34: =C34+D34+E34 -> 3868.9 | G34: =I6 -> 113.52 | H34: =B34-F34+G34 -> 2938.62
A35: Store 4 | B35: ='VertiPinturas Data Formats'!B8*'VertiPinturas Data Formats'!$B$38+'VertiPinturas Data Formats'!C8*'VertiPinturas Data Formats'!$C$38+'VertiPinturas Data Formats'!D8*'VertiPinturas Data Formats'!$D$38+'VertiPinturas Data Formats'!E8*'VertiPinturas Data Formats'!$E$38+'VertiPinturas Data Formats'!F8*'VertiPinturas Data Formats'!$F$38+'VertiPinturas Data Formats'!G8*'VertiPinturas Data Formats'!$G$38 -> 8360 | C35: =H7 -> 1140 | D35: =SUM(B27:G27) -> 3874.8 | E35: =H27 -> 68 | F35: =C35+D35+E35 -> 5082.8 | G35: =I7 -> 136.8 | H35: =B35-F35+G35 -> 3414
A36: Store 5 | B36: ='VertiPinturas Data Formats'!B9*'VertiPinturas Data Formats'!$B$38+'VertiPinturas Data Formats'!C9*'VertiPinturas Data Formats'!$C$38+'VertiPinturas Data Formats'!D9*'VertiPinturas Data Formats'!$D$38+'VertiPinturas Data Formats'!E9*'VertiPinturas Data Formats'!$E$38+'VertiPinturas Data Formats'!F9*'VertiPinturas Data Formats'!$F$38+'VertiPinturas Data Formats'!G9*'VertiPinturas Data Formats'!$G$38 -> 8452 | C36: =H8 -> 1172.6 | D36: =SUM(B28:G28) -> 4498.5 | E36: =H28 -> 106 | F36: =C36+D36+E36 -> 5777.1 | G36: =I8 -> 140.712 | H36: =B36-F36+G36 -> 2815.612
A37: Store 6 | B37: ='VertiPinturas Data Formats'!B10*'VertiPinturas Data Formats'!$B$38+'VertiPinturas Data Formats'!C10*'VertiPinturas Data Formats'!$C$38+'VertiPinturas Data Formats'!D10*'VertiPinturas Data Formats'!$D$38+'VertiPinturas Data Formats'!E10*'VertiPinturas Data Formats'!$E$38+'VertiPinturas Data Formats'!F10*'VertiPinturas Data Formats'!$F$38+'VertiPinturas Data Formats'!G10*'VertiPinturas Data Formats'!$G$38 -> 6304 | C37: =H9 -> 868 | D37: =SUM(B29:G29) -> 3654.2 | E37: =H29 -> 104 | F37: =C37+D37+E37 -> 4626.2 | G37: =I9 -> 69.44 | H37: =B37-F37+G37 -> 1747.24

Sheet VertiPinturas_formats
A1: DNI | B1: NAME | C1: ADDRESS | D1: GENDER | E1: POSITION | F1: DATE OF BIRTH | G1: SALARY | H1: SENIORITY | I1: AGE
A2: 123 | B2: NOMBRE 13 | C2: DIRECCIÓN 13 | D2: Mujer | E2: ADMINISTRATIVO/A | F2: 27508 | G2: 1800 | H2: 26.394521 | I2: 49.394521
A3: 234 | B3: NOMBRE 14 | C3: DIRECCIÓN 14 | D3: Mujer | E3: ADMINISTRATIVO/A | F3: 32609 | G3: 1350 | H3: 12.419178 | I3: 35.419178
A4: 56 | B4: NOMBRE 20 | C4: DIRECCIÓN 20 | D4: Mujer | E4: ADMINISTRATIVO/A | F4: 35608 | G4: 1670 | H4: 4.2027397 | I4: 27.20274
A5: 23 | B5: NOMBRE 21 | C5: DIRECCIÓN 21 | D5: Mujer | E5: ADMINISTRATIVO/A | F5: 25133 | G5: 1340 | H5: 32.90137 | I5: 55.90137
A6: 15 | B6: NOMBRE 22 | C6: DIRECCIÓN 22 | D6: Hombre | E6: ADMINISTRATIVO/A | F6: 24577 | G6: 1111 | H6: 34.424658 | I6: 57.424658
A7: 43 | B7: NOMBRE 27 | C7: DIRECCIÓN 27 | D7: Hombre | E7: ADMINISTRATIVO/A | F7: 34787 | G7: 1250 | H7: 6.4520548 | I7: 29.452055
A8: 567 | B8: NOMBRE 37 | C8: DIRECCIÓN 37 | D8: Hombre | E8: ADMINISTRATIVO/A | F8: 36276 | G8: 1455 | H8: 2.3726027 | I8: 25.372603
A9: 76 | B9: NOMBRE 39 | C9: DIRECCIÓN 39 | D9: Mujer | E9: ADMINISTRATIVO/A | F9: 29688 | G9: 1670 | H9: 20.421918 | I9: 43.421918
A10: 65 | B10: NOMBRE 4 | C10: DIRECCIÓN 4 | D10: Mujer | E10: ADMINISTRATIVO/A | F10: 29677 | G10: 2200 | H10: 20.452055 | I10: 43.452055
A11: 77 | B11: NOMBRE 47 | C11: DIRECCIÓN 47 | D11: Hombre | E11: ADMINISTRATIVO/A | F11: 29768 | G11: 2300 | H11: 20.20274 | I11: 43.20274
A12: 70 | B12: NOMBRE 5 | C12: DIRECCIÓN 5 | D12: Hombre | E12: ADMINISTRATIVO/A | F12: 24638 | G12: 2600 | H12: 34.257534 | I12: 57.257534
A13: 90 | B13: NOMBRE 9 | C13: DIRECCIÓN 9 | D13: Hombre | E13: ADMINISTRATIVO/A | F13: 32624 | G13: 2200 | H13: 12.378082 | I13: 35.378082
... A50: 85 | B50: NOMBRE 8 | C50: DIRECCIÓN 8 | D50: Hombre | E50: TÉCNICO/A | F50: 31922 | G50: 2100 | H50: 14.30137 | I50: 37.30137
